README.md
setup.py
probability_distributions_12b/Binomialdistribution.py
probability_distributions_12b/Gaussiandistribution.py
probability_distributions_12b/Generaldistribution.py
probability_distributions_12b/__init__.py
probability_distributions_12b.egg-info/PKG-INFO
probability_distributions_12b.egg-info/SOURCES.txt
probability_distributions_12b.egg-info/dependency_links.txt
probability_distributions_12b.egg-info/not-zip-safe
probability_distributions_12b.egg-info/top_level.txt