Metadata-Version: 2.1
Name: probability-distributions-12b
Version: 0.2
Summary: Gaussian and Binomial distributions
Home-page: UNKNOWN
Author-email: bucsab12@gmail.com
License: UNKNOWN
Platform: UNKNOWN
